sorted_fractionally_indexed_cowlist_set.py
sorted_fractionally_indexed_cowlist_set-0.1.0a0.dist-info/licenses/LICENSE
sorted_fractionally_indexed_cowlist_set-0.1.0a0.dist-info/METADATA
sorted_fractionally_indexed_cowlist_set-0.1.0a0.dist-info/WHEEL
sorted_fractionally_indexed_cowlist_set-0.1.0a0.dist-info/top_level.txt
sorted_fractionally_indexed_cowlist_set-0.1.0a0.dist-info/RECORD
