Metadata-Version: 2.4
Name: sorted-fractionally-indexed-cowlist-set
Version: 0.1.0a0
Summary: A Python package for managing a sorted, fractionally-indexed set of COWList containing elements within a given alphabet.
Author-email: Jifeng Wu <jifengwu2k@gmail.com>
License-Expression: MIT
Project-URL: Homepage, https://github.com/jifengwu2k/sorted-fractionally-indexed-cowlist-set
Project-URL: Bug Tracker, https://github.com/jifengwu2k/sorted-fractionally-indexed-cowlist-set/issues
Classifier: Programming Language :: Python :: 2
Classifier: Programming Language :: Python :: 3
Classifier: Operating System :: OS Independent
Requires-Python: >=2
License-File: LICENSE
Requires-Dist: canonical-range
Requires-Dist: cowlist
Requires-Dist: generalized-range
Requires-Dist: sortedcontainers
Requires-Dist: typing; python_version < "3.5"
Dynamic: license-file
